deepsecure/__init__.py
deepsecure/__main__.py
deepsecure/auth.py
deepsecure/client.py
deepsecure/exceptions.py
deepsecure/main.py
deepsecure/policy.py
deepsecure/types.py
deepsecure/utils.py
deepsecure/vault.py
deepsecure/_core/__init__.py
deepsecure/_core/agent_client.py
deepsecure/_core/audit_client.py
deepsecure/_core/audit_logger.py
deepsecure/_core/base_client.py
deepsecure/_core/client.py
deepsecure/_core/config.py
deepsecure/_core/delegation.py
deepsecure/_core/deployment_client.py
deepsecure/_core/environment_detector.py
deepsecure/_core/exceptions.py
deepsecure/_core/hardening_manager.py
deepsecure/_core/identity_manager.py
deepsecure/_core/identity_provider.py
deepsecure/_core/policy_client.py
deepsecure/_core/risk_client.py
deepsecure/_core/sandbox_manager.py
deepsecure/_core/scanner.py
deepsecure/_core/schemas.py
deepsecure/_core/vault_client.py
deepsecure/_core/crypto/__init__.py
deepsecure/_core/crypto/key_manager.py
deepsecure/commands/__init__.py
deepsecure/commands/agent.py
deepsecure/commands/audit.py
deepsecure/commands/configure.py
deepsecure/commands/deploy.py
deepsecure/commands/gateway.py
deepsecure/commands/harden.py
deepsecure/commands/ide.py
deepsecure/commands/inventory.py
deepsecure/commands/policy.py
deepsecure/commands/risk.py
deepsecure/commands/sandbox.py
deepsecure/commands/scan.py
deepsecure/commands/scorecard.py
deepsecure/commands/vault.py
deepsecure/integrations/__init__.py
deepsecure/integrations/aws_strands.py
deepsecure/integrations/base.py
deepsecure/integrations/crewai.py
deepsecure/integrations/langchain.py
deepsecure/resources/agent.py
deepsecure/resources/agents.py
deepsecure/resources/credential.py
deepsecure-0.1.10.dist-info/licenses/LICENSE
deeptrail-gateway/__init__.py
deeptrail-gateway/demo_integration.py
deeptrail-gateway/run_integration_tests.py
deeptrail-gateway/app/__init__.py
deeptrail-gateway/app/main.py
deeptrail-gateway/app/proxy.py
deeptrail-gateway/app/core/__init__.py
deeptrail-gateway/app/core/http_client.py
deepsecure-0.1.10.dist-info/METADATA
deepsecure-0.1.10.dist-info/WHEEL
deepsecure-0.1.10.dist-info/entry_points.txt
deepsecure-0.1.10.dist-info/top_level.txt
deepsecure-0.1.10.dist-info/RECORD
