Metadata-Version: 2.4
Name: deepsecure
Version: 0.1.10
Summary: DeepSecure: Secure your AI agent and agentic AI application ecosystem with DeepSecure.
Author-email: DeepSecure Team <mahendra@deeptrail.com>
License-Expression: Apache-2.0
Project-URL: Homepage, https://github.com/DeepTrail/deepsecure
Project-URL: Bug Tracker, https://github.com/DeepTrail/deepsecure/issues
Project-URL: Documentation, https://github.com/DeepTrail/deepsecure/
Keywords: security,ai,cli,credentials,vault,policy,sandbox
Classifier: Programming Language :: Python :: 3
Classifier: Programming Language :: Python :: 3.9
Classifier: Programming Language :: Python :: 3.10
Classifier: Programming Language :: Python :: 3.11
Classifier: Operating System :: OS Independent
Classifier: Environment :: Console
Classifier: Intended Audience :: Developers
Classifier: Intended Audience :: Information Technology
Classifier: Intended Audience :: System Administrators
Classifier: Topic :: Security
Classifier: Topic :: Software Development :: Libraries :: Python Modules
Requires-Python: >=3.9
License-File: LICENSE
Requires-Dist: typer[all]
Requires-Dist: requests
Requires-Dist: keyring
Requires-Dist: pyjwt[crypto]
Requires-Dist: pydantic
Requires-Dist: toml
Requires-Dist: rich
Provides-Extra: dev
Requires-Dist: pytest; extra == "dev"
Requires-Dist: pytest-cov; extra == "dev"
Requires-Dist: responses; extra == "dev"
Provides-Extra: frameworks
Requires-Dist: crewai; extra == "frameworks"
Requires-Dist: langchain>=0.1.0; extra == "frameworks"
Requires-Dist: langchain-community>=0.0.10; extra == "frameworks"
Requires-Dist: fastapi; extra == "frameworks"
Requires-Dist: uvicorn; extra == "frameworks"
Provides-Extra: lint
Requires-Dist: black>=23.0.0; extra == "lint"
Requires-Dist: isort>=5.12.0; extra == "lint"
Requires-Dist: ruff>=0.1.0; extra == "lint"
Requires-Dist: mypy>=1.0.0; extra == "lint"
Provides-Extra: test
Requires-Dist: pytest>=7.0.0; extra == "test"
Requires-Dist: pytest-cov>=4.0.0; extra == "test"
Requires-Dist: pytest-asyncio>=0.21.0; extra == "test"
Requires-Dist: pytest-mock>=3.10.0; extra == "test"
Requires-Dist: responses>=0.23.0; extra == "test"
Requires-Dist: httpx>=0.24.0; extra == "test"
Provides-Extra: docs
Requires-Dist: mkdocs>=1.5.0; extra == "docs"
Requires-Dist: mkdocs-material>=9.0.0; extra == "docs"
Requires-Dist: mkdocstrings[python]>=0.22.0; extra == "docs"
Requires-Dist: mkdocs-gen-files>=0.5.0; extra == "docs"
Provides-Extra: build
Requires-Dist: build>=0.10.0; extra == "build"
Requires-Dist: twine>=4.0.0; extra == "build"
Requires-Dist: wheel>=0.40.0; extra == "build"
Provides-Extra: security
Requires-Dist: bandit>=1.7.0; extra == "security"
Requires-Dist: safety>=2.3.0; extra == "security"
Provides-Extra: perf
Requires-Dist: py-spy>=0.3.0; extra == "perf"
Requires-Dist: memory-profiler>=0.60.0; extra == "perf"
Provides-Extra: all-dev
Requires-Dist: deepsecure[build,dev,docs,lint,security,test]; extra == "all-dev"
Dynamic: license-file
